setup.py
dexpy/__init__.py
dexpy/alias.py
dexpy/box_behnken.py
dexpy/ccd.py
dexpy/cox_effects.py
dexpy/design.py
dexpy/effects.py
dexpy/eval.py
dexpy/factorial.py
dexpy/model.py
dexpy/optimal.py
dexpy/power.py
dexpy/samplers.py
dexpy/simplex_centroid.py
dexpy/simplex_lattice.py
dexpy.egg-info/PKG-INFO
dexpy.egg-info/SOURCES.txt
dexpy.egg-info/dependency_links.txt
dexpy.egg-info/requires.txt
dexpy.egg-info/top_level.txt
dexpy/tests/__init__.py
dexpy/tests/test_alias.py
dexpy/tests/test_box_behnken.py
dexpy/tests/test_ccd.py
dexpy/tests/test_cox_effects.py
dexpy/tests/test_design.py
dexpy/tests/test_effects.py
dexpy/tests/test_factorial.py
dexpy/tests/test_load.py
dexpy/tests/test_model_matrix.py
dexpy/tests/test_optimal.py
dexpy/tests/test_power.py
dexpy/tests/test_samplers.py
dexpy/tests/test_simplex_centroid.py
dexpy/tests/test_simplex_lattice.py