Metadata-Version: 1.1
Name: dexpy
Version: 0.12
Summary: dexpy: Design of Experiments (DOE) for Python.
Home-page: https://statease.github.io/dexpy/
Author: Hank Anderson, Martin Bezener
Author-email: hank@statease.com
License: apache
Download-URL: https://github.com/statease/dexpy/releases
Platform: UNKNOWN
Classifier: Development Status :: 2 - Pre-Alpha
Classifier: Intended Audience :: Manufacturing
Classifier: Intended Audience :: Science/Research
Classifier: License :: OSI Approved :: Apache Software License
Classifier: Programming Language :: Python
Classifier: Programming Language :: Python :: 2
Classifier: Programming Language :: Python :: 3
Classifier: Topic :: Scientific/Engineering :: Mathematics
